MANIFEST.in
README.rst
setup.py
urlclean.py
plugins/__init__.py
plugins/indavideo.py
plugins/test.py
urlclean.egg-info/PKG-INFO
urlclean.egg-info/SOURCES.txt
urlclean.egg-info/dependency_links.txt
urlclean.egg-info/requires.txt
urlclean.egg-info/top_level.txt