Metadata-Version: 1.1
Name: urlclean
Version: 0.5.4
Summary: Utilities to clean up URLs 
Home-page: http://packages.python.org/urlclean
Author: Stefan Marsiske
Author-email: stefan.marsiske@gmail.com
License: AGPLv3+
Keywords: URL HTTP sanitizing privacy
Platform: UNKNOWN
Classifier: Development Status :: 4 - Beta
Classifier: License :: OSI Approved :: GNU Affero General Public License v3
Classifier: Environment :: Web Environment
Classifier: Topic :: Internet :: WWW/HTTP
Classifier: Topic :: Internet :: WWW/HTTP :: HTTP Servers
Classifier: Topic :: Security
Classifier: Topic :: Security :: Cryptography
